BetterMaths/__init__.py
BetterMaths/main.py
BetterMaths/main.pyi
BetterMaths/geometry/__init__.py
BetterMaths/geometry/main.py
BetterMaths/probability/__init__.py
BetterMaths/probability/main.py
BetterMaths/sequences/__init__.py
BetterMaths/sequences/main.py
BetterMaths/solidGeometry/__init__.py
BetterMaths/solidGeometry/main.py
bettermaths-0.0.4.dist-info/METADATA
bettermaths-0.0.4.dist-info/WHEEL
bettermaths-0.0.4.dist-info/licenses/LICENSE
bettermaths-0.0.4.dist-info/RECORD
