Metadata-Version: 2.3
Name: BetterMaths
Version: 0.0.4
Summary: Python mathematics made easier
Project-URL: Homepage, https://dhaiven.github.io/
Project-URL: Documentation, https://github.com/Dhaiven/BetterMaths/wiki
Project-URL: Repository, https://github.com/Dhaiven/BetterMaths
Author-email: Dhaiven <bettermath.get.help@gmail.com>, algorythmTTV <bettermath.get.help@gmail.com>
License-File: LICENSE
Keywords: better,easier,easy,math,mathematics,simple
Classifier: License :: OSI Approved :: MIT License
Classifier: Operating System :: OS Independent
Classifier: Programming Language :: Python :: 3.4
Classifier: Programming Language :: Python :: 3.5
Classifier: Programming Language :: Python :: 3.6
Classifier: Programming Language :: Python :: 3.7
Classifier: Programming Language :: Python :: 3.8
Classifier: Programming Language :: Python :: 3.9
Classifier: Programming Language :: Python :: 3.10
Classifier: Programming Language :: Python :: 3.11
Classifier: Programming Language :: Python :: 3.12
Requires-Python: >=3.4
Requires-Dist: sympy
